pycci/__init__.py
pycci/api.py
pycci/config.py
pycci/config.yaml
pycci/jobtype.py
pycci/models.py
pycci-1.0.0.dist-info/METADATA
pycci-1.0.0.dist-info/WHEEL
pycci-1.0.0.dist-info/top_level.txt
pycci-1.0.0.dist-info/RECORD
