Metadata-Version: 2.1
Name: pycci
Version: 1.0.0
Summary: CircleCI API written in python
Home-page: https://github.com/winslowdibona/pycci
Author: Winslow DiBona
License: MIT
Platform: UNKNOWN
Requires-Dist: pyyaml
Requires-Dist: requests
